exptime.py
exptime-0.2.0.dist-info/METADATA
exptime-0.2.0.dist-info/WHEEL
exptime-0.2.0.dist-info/top_level.txt
exptime-0.2.0.dist-info/RECORD
