Metadata-Version: 2.4
Name: exptime
Version: 0.2.0
Summary: Simple timeout-based exception helpers.
Author: wirnty
Author-email: skedovichusjdj@gmail.com
Requires-Python: >=3.6
Dynamic: author
Dynamic: author-email
Dynamic: requires-python
Dynamic: summary
